conviction_python/__init__.py
conviction_python/conviction.py
conviction_python-0.1.0.1.dist-info/METADATA
conviction_python-0.1.0.1.dist-info/WHEEL
conviction_python-0.1.0.1.dist-info/licenses/LICENSE
conviction_python-0.1.0.1.dist-info/RECORD
